pulumi_tailscale_native/__init__.py
pulumi_tailscale_native/_utilities.py
pulumi_tailscale_native/provider.py
pulumi_tailscale_native/pulumi-plugin.json
pulumi_tailscale_native/py.typed
pulumi_tailscale_native/config/__init__.py
pulumi_tailscale_native/config/__init__.pyi
pulumi_tailscale_native/config/vars.py
pulumi_tailscale_native/device/__init__.py
pulumi_tailscale_native/device/authorize_device.py
pulumi_tailscale_native/device/get_device.py
pulumi_tailscale_native/device/get_routes_config.py
pulumi_tailscale_native/device/key_expiry.py
pulumi_tailscale_native/device/outputs.py
pulumi_tailscale_native/device/routes_config.py
pulumi_tailscale_native/device/tags.py
pulumi_tailscale_native/tailnet/__init__.py
pulumi_tailscale_native/tailnet/_enums.py
pulumi_tailscale_native/tailnet/_inputs.py
pulumi_tailscale_native/tailnet/acl.py
pulumi_tailscale_native/tailnet/dns_preferences_config.py
pulumi_tailscale_native/tailnet/get_acl.py
pulumi_tailscale_native/tailnet/get_dns_preferences_config.py
pulumi_tailscale_native/tailnet/get_key.py
pulumi_tailscale_native/tailnet/get_name_servers_config.py
pulumi_tailscale_native/tailnet/key.py
pulumi_tailscale_native/tailnet/list_devices.py
pulumi_tailscale_native/tailnet/list_keys.py
pulumi_tailscale_native/tailnet/list_search_paths.py
pulumi_tailscale_native/tailnet/name_servers_config.py
pulumi_tailscale_native/tailnet/outputs.py
pulumi_tailscale_native/tailnet/replace_search_paths.py
pulumi_tailscale_native-0.1.6.dist-info/METADATA
pulumi_tailscale_native-0.1.6.dist-info/WHEEL
pulumi_tailscale_native-0.1.6.dist-info/top_level.txt
pulumi_tailscale_native-0.1.6.dist-info/RECORD
